sonicparanoid/__init__.py
sonicparanoid/archiver.cpython-37m-darwin.so
sonicparanoid/blast_tools.py
sonicparanoid/colored_output.py
sonicparanoid/essentials_c.cpython-37m-darwin.so
sonicparanoid/extract_results.py
sonicparanoid/get_test_data.py
sonicparanoid/graph_c.cpython-37m-darwin.so
sonicparanoid/hdr_mapping.py
sonicparanoid/inpyranoid.py
sonicparanoid/inpyranoid_c.cpython-37m-darwin.so
sonicparanoid/length_difference_filter.py
sonicparanoid/mcl_c.cpython-37m-darwin.so
sonicparanoid/mmseqs_parser_c.cpython-37m-darwin.so
sonicparanoid/mmseqs_parser_cython.py
sonicparanoid/orthogroups.py
sonicparanoid/ortholog_detection.py
sonicparanoid/process_output.py
sonicparanoid/remap_tables_c.cpython-37m-darwin.so
sonicparanoid/seq_tools.py
sonicparanoid/set_mmseqs2.py
sonicparanoid/sonic_paranoid.py
sonicparanoid/sonic_paranoid_extract.py
sonicparanoid/sys_tools.py
sonicparanoid/test_blast_tools.py
sonicparanoid/test_graph.py
sonicparanoid/test_hdr_mapping.py
sonicparanoid/test_length_difference_filter.py
sonicparanoid/test_mcl.py
sonicparanoid/test_mmseqs_parser_cython.py
sonicparanoid/test_orthogroups.py
sonicparanoid/test_ortholog_detection.py
sonicparanoid/test_reads_stats.py
sonicparanoid/test_seq_tools.py
sonicparanoid/test_sonicparanoid.py
sonicparanoid/test_sys_tools.py
sonicparanoid/test_workers.py
sonicparanoid/workers.py
sonicparanoid/bin/README.txt
sonicparanoid/bin/guess_fast_pair.pckl
sonicparanoid/example/test_input/chlamydia_trachomatis
sonicparanoid/example/test_input/deinococcus_radiodurans
sonicparanoid/example/test_input/gloeobacter_violaceus
sonicparanoid/example/test_input/thermotoga_maritima
sonicparanoid/example/test_output/README.txt
sonicparanoid/mcl_package/mcl_darwin_brew
sonicparanoid/mcl_package/mcl_darwin_llvm9_clang1103
sonicparanoid/mcl_package/mcl_linux
sonicparanoid/mcl_package/mcl_src_slim.tar.gz
sonicparanoid/mmseqs2_src/README.txt
sonicparanoid/mmseqs2_src/mmseqs_linux_avx2.zip
sonicparanoid/mmseqs2_src/mmseqs_linux_sse41.zip
sonicparanoid-1.3.5.dist-info/LICENSE.md
sonicparanoid-1.3.5.dist-info/METADATA
sonicparanoid-1.3.5.dist-info/WHEEL
sonicparanoid-1.3.5.dist-info/entry_points.txt
sonicparanoid-1.3.5.dist-info/top_level.txt
sonicparanoid-1.3.5.dist-info/RECORD
