Metadata-Version: 2.1
Name: sonicparanoid
Version: 1.3.5
Summary: SonicParanoid: fast, easy and accurate orthology inference
Home-page: http://iwasakilab.bs.s.u-tokyo.ac.jp/sonicparanoid/
Author: Salvatore Cosentino
Author-email: salvo@gmail.com
License: GNU GENERAL PUBLIC LICENSE, Version 3.0 (GPLv3)
Project-URL: Source, https://gitlab.com/salvo981/sonicparanoid2
Keywords: bioinformatic inparanoid orthology_inference phylogeny evolution orthology
Platform: UNKNOWN
Classifier: Development Status :: 5 - Production/Stable
Classifier: Environment :: Console
Classifier: Intended Audience :: Science/Research
Classifier: Operating System :: MacOS :: MacOS X
Classifier: Operating System :: POSIX
Classifier: Operating System :: Unix
Classifier: Topic :: Scientific/Engineering
Classifier: Topic :: Scientific/Engineering :: Bio-Informatics
Classifier: License :: OSI Approved :: GNU General Public License v3 (GPLv3)
Classifier: Programming Language :: Python :: 3.6
Classifier: Programming Language :: Python :: 3.7
Classifier: Programming Language :: Python :: 3.8
Requires-Python: >=3.6, <3.9
Requires-Dist: scipy (>=1.2.1)
Requires-Dist: numpy (>=1.18.0)
Requires-Dist: pandas (>=1.0.0)
Requires-Dist: cython (>=0.29.0)
Requires-Dist: setuptools (>=24.2.0)
Requires-Dist: pip (>=9.0.1)
Requires-Dist: biopython (>=1.73)
Requires-Dist: mypy (>=0.720)
Requires-Dist: psutil (>=5.6.0)
Requires-Dist: scikit-learn (>=0.22.0)
Requires-Dist: wheel (>=0.32.0)
Requires-Dist: filetype (>=1.0.7)
